flowjax/__init__.py
flowjax/distributions.py
flowjax/flows.py
flowjax/masks.py
flowjax/py.typed
flowjax/root_finding.py
flowjax/tasks.py
flowjax/utils.py
flowjax/bijections/__init__.py
flowjax/bijections/affine.py
flowjax/bijections/bijection.py
flowjax/bijections/block_autoregressive_network.py
flowjax/bijections/chain.py
flowjax/bijections/concatenate.py
flowjax/bijections/coupling.py
flowjax/bijections/exp.py
flowjax/bijections/jax_transforms.py
flowjax/bijections/masked_autoregressive.py
flowjax/bijections/orthogonal.py
flowjax/bijections/planar.py
flowjax/bijections/power.py
flowjax/bijections/rational_quadratic_spline.py
flowjax/bijections/sigmoid.py
flowjax/bijections/softplus.py
flowjax/bijections/tanh.py
flowjax/bijections/utils.py
flowjax/experimental/__init__.py
flowjax/experimental/numpyro.py
flowjax/train/__init__.py
flowjax/train/loops.py
flowjax/train/losses.py
flowjax/train/train_utils.py
flowjax-18.0.0.dist-info/METADATA
flowjax-18.0.0.dist-info/WHEEL
flowjax-18.0.0.dist-info/licenses/LICENSE
flowjax-18.0.0.dist-info/RECORD
