Metadata-Version: 2.4
Name: flowjax
Version: 18.0.0
Summary: Easy to use distributions, bijections and normalizing flows in JAX.
Project-URL: repository, https://github.com/danielward27/flowjax
Project-URL: documentation, https://danielward27.github.io/flowjax/index.html
Author-email: Daniel Ward <danielward27@outlook.com>
License: The MIT License (MIT)
License-File: LICENSE
Keywords: equinox,jax,neural-networks
Classifier: Intended Audience :: Science/Research
Classifier: License :: OSI Approved :: MIT License
Classifier: Natural Language :: English
Classifier: Programming Language :: Python :: 3
Classifier: Topic :: Scientific/Engineering :: Artificial Intelligence
Classifier: Topic :: Scientific/Engineering :: Information Analysis
Classifier: Topic :: Scientific/Engineering :: Mathematics
Requires-Python: >=3.10
Requires-Dist: equinox>=0.10
Requires-Dist: jax>=0.4.16
Requires-Dist: jaxtyping
Requires-Dist: optax
Requires-Dist: paramax>=0.0.5
Requires-Dist: tqdm
Provides-Extra: dev
Requires-Dist: beartype; extra == 'dev'
Requires-Dist: ipython; extra == 'dev'
Requires-Dist: nbsphinx; extra == 'dev'
Requires-Dist: numpyro>=0.20.0; extra == 'dev'
Requires-Dist: pytest; extra == 'dev'
Requires-Dist: ruff; extra == 'dev'
Requires-Dist: sphinx-autodoc-typehints; extra == 'dev'
Requires-Dist: sphinx-book-theme; extra == 'dev'
Requires-Dist: sphinx-copybutton; extra == 'dev'
Requires-Dist: sphinx<8.2; extra == 'dev'
